{
  "employees": [
    {
      "id": 2,
      "firstName": "Dipanshu",
      "lastName": "verma",
      "email": "vermadipanshu444@gmail.com",
      "department": "Tech",
      "salary": "2222222",
      "date": "2024-01-22"
    },
    {
      "id": 3,
      "firstName": "Dipanshu",
      "lastName": "verma",
      "email": "vermadipanshu444@gmail.com",
      "department": "Tech",
      "salary": "2222222",
      "date": "2024-01-22"
    },{
      "id": 4,
      "firstName": "Dipanshu",
      "lastName": "verma",
      "email": "vermadipanshu444@gmail.com",
      "department": "Tech",
      "salary": "2222222",
      "date": "2024-01-22"
    }
    ,{
      "id": 5,
      "firstName": "Dipanshu",
      "lastName": "verma",
      "email": "vermadipanshu444@gmail.com",
      "department": "Tech",
      "salary": "2222222",
      "date": "2024-01-22"
    }
    ,{
      "id": 6,
      "firstName": "Dipanshu",
      "lastName": "verma",
      "email": "vermadipanshu444@gmail.com",
      "department": "Tech",
      "salary": "2222222",
      "date": "2024-01-22"
    },{
      "id": 7,
      "firstName": "Dipanshu",
      "lastName": "verma",
      "email": "vermadipanshu444@gmail.com",
      "department": "Tech",
      "salary": "2222222",
      "date": "2024-01-22"
    }
    ,{
      "id": 8,
      "firstName": "Dipanshu",
      "lastName": "verma",
      "email": "vermadipanshu444@gmail.com",
      "department": "Tech",
      "salary": "2222222",
      "date": "2024-01-22"
    }
    ,
    {
      "id": 9,
      "firstName": "Dipanshu",
      "lastName": "verma",
      "email": "vermadipanshu444@gmail.com",
      "department": "Tech",
      "salary": "2222222",
      "date": "2024-01-22"
    },
    {
      "id": 10,
      "firstName": "devil",
      "lastName": "verma",
      "email": "vermadipanshu444@gmail.com",
      "department": "Tech",
      "salary": "2222222",
      "date": "2024-01-22"
    },
    {
      "id": 11,
      "firstName": "Dipanshu",
      "lastName": "verma",
      "email": "vermadipanshu444@gmail.com",
      "department": "Tech",
      "salary": "2222222",
      "date": "2024-01-22"
    }
  ]
}